rtmp_streaming.cp310-win_amd64.pyd
rtmp_streaming-0.0.5.dist-info/LICENSE.txt
rtmp_streaming-0.0.5.dist-info/METADATA
rtmp_streaming-0.0.5.dist-info/WHEEL
rtmp_streaming-0.0.5.dist-info/top_level.txt
rtmp_streaming-0.0.5.dist-info/RECORD
