Metadata-Version: 2.1
Name: rtmp_streaming
Version: 0.0.5
Summary: rtmp streaming using double buffer
Author: andrea nobile
Author-email: 
Requires-Python: >=3.6
License-File: LICENSE.txt
Provides-Extra: test
Requires-Dist: pytest >=6.0 ; extra == 'test'
